framework/__init__.py
framework/framework.py
framework/main.py
xursparks/__init__.py
xursparks/error/__init__.py
xursparks/error/main.py
xursparks/services/__init__.py
xursparks/services/itemreader.py
xursparks/services/main.py
xursparks/services/google/__init__.py
xursparks/services/google/google_service.py
xursparks/services/google/main.py
xursparks/services/http/__init__.py
xursparks/services/http/api_reader.py
xursparks/services/http/api_service.py
xursparks/services/http/main.py
xursparks/tools/__init__.py
xursparks/tools/encryption.py
xursparks/tools/excelreader.py
xursparks/tools/excelwriter.py
xursparks/tools/logger.py
xursparks/tools/main.py
xursparks/xkynet/__init__.py
xursparks/xkynet/main.py
xursparks/xkynet/nlp/__init__.py
xursparks/xkynet/nlp/finance.py
xursparks/xkynet/nlp/hr.py
xursparks/xkynet/nlp/nlp.py
xursparks-1.2.10.dist-info/METADATA
xursparks-1.2.10.dist-info/WHEEL
xursparks-1.2.10.dist-info/top_level.txt
xursparks-1.2.10.dist-info/RECORD
