Metadata-Version: 2.4
Name: xursparks
Version: 1.2.10
Summary: Encapsulating Apache Spark for Easy Usage
Home-page: https://github.com/dev-doods687/xursparks
Author: Randell Gabriel Santos
Author-email: randellsantos@gmail.com
License: MIT
Classifier: Development Status :: 5 - Production/Stable
Classifier: Programming Language :: Python :: 3
Classifier: License :: OSI Approved :: MIT License
Classifier: Operating System :: OS Independent
Requires-Python: >=3.10
Requires-Dist: setuptools
Requires-Dist: wheel
Requires-Dist: twine
Requires-Dist: requests
Requires-Dist: numpy==1.26.4
Requires-Dist: pandas
Requires-Dist: pyspark==3.5.2
Requires-Dist: boto3
Requires-Dist: openpyxl
Requires-Dist: xurpas_data_quality
Requires-Dist: openai==1.54.5
Requires-Dist: langchain==0.2.17
Requires-Dist: langchain_community==0.2.19
Requires-Dist: langchain_core==0.2.43
Requires-Dist: langchain_openai==0.1.20
Requires-Dist: llama_index==0.10.39
Requires-Dist: llama_index.core==0.10.68.post1
Requires-Dist: langchain_experimental==0.0.65
Requires-Dist: tabulate==0.9.0
Requires-Dist: PyMuPDF==1.24.14
Requires-Dist: llama-index-llms-langchain==0.3.0
Requires-Dist: PyHive==0.7.0
Requires-Dist: thrift>=0.12.0
Requires-Dist: cryptography==45.0.4
Requires-Dist: autopep8>=2.3.2
Requires-Dist: requests_ntlm>=1.3.0
Requires-Dist: google-auth-oauthlib==1.2.2
Requires-Dist: google-auth-httplib2==0.2.0
Requires-Dist: google-api-python-client==2.184.0
Dynamic: author
Dynamic: author-email
Dynamic: classifier
Dynamic: description
Dynamic: description-content-type
Dynamic: home-page
Dynamic: license
Dynamic: requires-dist
Dynamic: requires-python
Dynamic: summary
